diffeqpy/__init__.py
diffeqpy/amdgpu.py
diffeqpy/cuda.py
diffeqpy/de.py
diffeqpy/metal.py
diffeqpy/ode.py
diffeqpy/oneapi.py
diffeqpy/tests/__init__.py
diffeqpy/tests/test_dae.py
diffeqpy/tests/test_dde.py
diffeqpy/tests/test_ode.py
diffeqpy/tests/test_ode_ordinarydiffeq.py
diffeqpy/tests/test_sde.py
diffeqpy-2.5.5.dist-info/LICENSE.md
diffeqpy-2.5.5.dist-info/METADATA
diffeqpy-2.5.5.dist-info/WHEEL
diffeqpy-2.5.5.dist-info/top_level.txt
diffeqpy-2.5.5.dist-info/RECORD
