Metadata-Version: 2.1
Name: diffeqpy
Version: 2.5.5
Summary: Solving Differential Equations in Python
Home-page: http://github.com/SciML/diffeqpy
Author: Chris Rackauckas and Takafumi Arakaki
Author-email: contact@sciml.ai
License: MIT
Keywords: differential equations stochastic ordinary delay differential-algebraic dae ode sde dde oneapi AMD ROCm CUDA Metal GPU
Platform: UNKNOWN
Classifier: Development Status :: 4 - Beta
Classifier: License :: OSI Approved :: MIT License
Classifier: Programming Language :: Python :: 3.10
Classifier: Programming Language :: Python :: 3.11
Classifier: Programming Language :: Python :: 3.12
Classifier: Programming Language :: Python :: 3.13
Classifier: Programming Language :: Python :: 3.14
Classifier: Topic :: Scientific/Engineering :: Mathematics
Classifier: Topic :: Scientific/Engineering :: Physics
Requires-Python: >=3.10
License-File: LICENSE.md
Requires-Dist: juliacall (>=0.9.28)
Requires-Dist: jill
